{
  "scenarioName": "scenario-01-input-500-Mib",
  "resourceConfigStrategy": "StepConfConfigStrategy",
  "inputDataSizeMib": 500.7261505126953,
  "sloMs": 109020,
  "workflowOutput": {
    "executionTimeMs": 186069,
    "totalCost": 0.008658,
    "data": {
      "sizeBytes": 37873978
    },
    "stepLogs": {
      "validate-video": {
        "resourceProfile": {
          "memoryMiB": 2048,
          "milliCpu": 1000,
          "price100Ms": 0.00000406
        },
        "executionTimeMs": 119,
        "executionCost": 0.000008
      },
      "cut-video-segment-a": {
        "resourceProfile": {
          "memoryMiB": 1024,
          "milliCpu": 583,
          "price100Ms": 0.00000231
        },
        "executionTimeMs": 184358,
        "executionCost": 0.00426
      },
      "cut-video-segment-b": {
        "resourceProfile": {
          "memoryMiB": 1024,
          "milliCpu": 583,
          "price100Ms": 0.00000231
        },
        "executionTimeMs": 184358,
        "executionCost": 0.00426
      },
      "merge-videos": {
        "resourceProfile": {
          "memoryMiB": 4096,
          "milliCpu": 2000,
          "price100Ms": 0.00000812
        },
        "executionTimeMs": 1592,
        "executionCost": 0.00013
      }
    }
  },
  "sloFulfilled": false
}
