{
  "scenarioName": "scenario-02-input-227-Mib",
  "resourceConfigStrategy": "SlamConfigStrategy",
  "inputDataSizeMib": 227.84742832183838,
  "sloMs": 77420,
  "strategyTrainingOutput": {
    "workflowOutput": {
      "executionTimeMs": 58473,
      "totalCost": 0.105683,
      "data": {
        "sizeBytes": 23841366
      },
      "stepLogs": {
        "validate-video": {
          "resourceProfile": {
            "memoryMiB": 256,
            "milliCpu": 167,
            "price100Ms": 6.48e-7
          },
          "executionTimeMs": 636,
          "executionCost": 0.000005,
          "resourceConfigStrategyExecutionTimeMs": 0
        },
        "cut-video-segment-a": {
          "resourceProfile": {
            "memoryMiB": 16384,
            "milliCpu": 4000,
            "price100Ms": 0.0001904
          },
          "executionTimeMs": 27616,
          "executionCost": 0.052741,
          "resourceConfigStrategyExecutionTimeMs": 0
        },
        "cut-video-segment-b": {
          "resourceProfile": {
            "memoryMiB": 16384,
            "milliCpu": 4000,
            "price100Ms": 0.0001904
          },
          "executionTimeMs": 27616,
          "executionCost": 0.052741,
          "resourceConfigStrategyExecutionTimeMs": 0
        },
        "merge-videos": {
          "resourceProfile": {
            "memoryMiB": 256,
            "milliCpu": 167,
            "price100Ms": 6.48e-7
          },
          "executionTimeMs": 30221,
          "executionCost": 0.000196,
          "resourceConfigStrategyExecutionTimeMs": 0
        }
      },
      "avgResourceConfigStrategyExecutionTimeMs": 0
    },
    "stepConfigs": {
      "validate-video": {
        "memoryMiB": 256,
        "milliCpu": 167,
        "price100Ms": 6.48e-7
      },
      "cut-video-segment-a": {
        "memoryMiB": 16384,
        "milliCpu": 4000,
        "price100Ms": 0.0001904
      },
      "cut-video-segment-b": {
        "memoryMiB": 16384,
        "milliCpu": 4000,
        "price100Ms": 0.0001904
      },
      "merge-videos": {
        "memoryMiB": 256,
        "milliCpu": 167,
        "price100Ms": 6.48e-7
      }
    }
  },
  "workflowOutput": {
    "executionTimeMs": 57550,
    "totalCost": 0.105677,
    "data": {
      "sizeBytes": 37873978
    },
    "stepLogs": {
      "validate-video": {
        "resourceProfile": {
          "memoryMiB": 256,
          "milliCpu": 167,
          "price100Ms": 6.48e-7
        },
        "executionTimeMs": 636,
        "executionCost": 0.000005,
        "resourceConfigStrategyExecutionTimeMs": 0
      },
      "cut-video-segment-a": {
        "resourceProfile": {
          "memoryMiB": 16384,
          "milliCpu": 4000,
          "price100Ms": 0.0001904
        },
        "executionTimeMs": 27616,
        "executionCost": 0.052741,
        "resourceConfigStrategyExecutionTimeMs": 0
      },
      "cut-video-segment-b": {
        "resourceProfile": {
          "memoryMiB": 16384,
          "milliCpu": 4000,
          "price100Ms": 0.0001904
        },
        "executionTimeMs": 27616,
        "executionCost": 0.052741,
        "resourceConfigStrategyExecutionTimeMs": 0
      },
      "merge-videos": {
        "resourceProfile": {
          "memoryMiB": 256,
          "milliCpu": 167,
          "price100Ms": 6.48e-7
        },
        "executionTimeMs": 29298,
        "executionCost": 0.00019,
        "resourceConfigStrategyExecutionTimeMs": 0
      }
    },
    "avgResourceConfigStrategyExecutionTimeMs": 0
  },
  "sloFulfilled": true
}
